pz_rail_flexzboost-1.2.3.dist-info/licenses/LICENSE
rail/estimation/algos/flexzboost.py
rail/flexzboost/__init__.py
rail/flexzboost/_version.py
pz_rail_flexzboost-1.2.3.dist-info/METADATA
pz_rail_flexzboost-1.2.3.dist-info/WHEEL
pz_rail_flexzboost-1.2.3.dist-info/top_level.txt
pz_rail_flexzboost-1.2.3.dist-info/RECORD
